cleaning.py
merge.py
parse.py
readweb.py
topics.py
preparation/__init__.py
preparation/cleaning.py
preparation/filter.py
preparation/merge.py
preparation/parse.py
preparation/readweb.py
preparation/topics.py
collegepreparation-0.1.dist-info/LICENSE.txt
collegepreparation-0.1.dist-info/METADATA
collegepreparation-0.1.dist-info/WHEEL
collegepreparation-0.1.dist-info/top_level.txt
collegepreparation-0.1.dist-info/RECORD
